{
  "available_vessels": {
    "PSV_1": {
      "return_time": 80
    },
    "SPOT": {
      "return_time": 80
    }
  },
  "discretization_parameter": 4.0,
  "installation_ordering": "random",
  "orders": {
    "0": {
      "installation": 6,
      "mandatory": "True",
      "size": 95.0,
      "transport": "delivery"
    },
    "1": {
      "installation": 3,
      "mandatory": "True",
      "size": 137.0,
      "transport": "delivery"
    },
    "2": {
      "installation": 21,
      "mandatory": "True",
      "size": 231.0,
      "transport": "delivery"
    },
    "3": {
      "installation": 23,
      "mandatory": "True",
      "size": 150.0,
      "transport": "delivery"
    },
    "4": {
      "installation": 15,
      "mandatory": "False",
      "size": 94.0,
      "transport": "delivery"
    },
    "5": {
      "installation": 17,
      "mandatory": "False",
      "size": 76.0,
      "transport": "delivery"
    },
    "6": {
      "installation": 2,
      "mandatory": "False",
      "size": 116.0,
      "transport": "pickup"
    },
    "7": {
      "installation": 23,
      "mandatory": "False",
      "size": 193.0,
      "transport": "pickup"
    }
  },
  "planning_period_hours": 80.0,
  "random_seed": 10,
  "weather_scenario": "perfect"
}